Workbook

Sheet Resumen
A1: Resumen de cumplimiento por agencia
A2: Se recalcula automáticamente si se modifican los estados en la hoja Comparativo. Puntaje: Cumple=1, Parcial=0,5, resto=0.
A4: Estado | B4: Dannemann | C4: Buzios Tour | D4: InMotion
A5: Cumple | B5: =COUNTIF(Comparativo!E$5:E$40,$A5) -> 1 | C5: =COUNTIF(Comparativo!G$5:G$40,$A5) -> 7 | D5: =COUNTIF(Comparativo!I$5:I$40,$A5) -> 3
A6: Parcial | B6: =COUNTIF(Comparativo!E$5:E$40,$A6) -> 6 | C6: =COUNTIF(Comparativo!G$5:G$40,$A6) -> 14 | D6: =COUNTIF(Comparativo!I$5:I$40,$A6) -> 4
A7: No cumple | B7: =COUNTIF(Comparativo!E$5:E$40,$A7) -> 20 | C7: =COUNTIF(Comparativo!G$5:G$40,$A7) -> 9 | D7: =COUNTIF(Comparativo!I$5:I$40,$A7) -> 15
A8: No informa | B8: =COUNTIF(Comparativo!E$5:E$40,$A8) -> 9 | C8: =COUNTIF(Comparativo!G$5:G$40,$A8) -> 6 | D8: =COUNTIF(Comparativo!I$5:I$40,$A8) -> 14
A9: Total requisitos | B9: =SUM(B5:B8) -> 36 | C9: =SUM(C5:C8) -> 36 | D9: =SUM(D5:D8) -> 36
A10: Puntaje (Cumple + ½ Parcial) | B10: =B5+0.5*B6 -> 4 | C10: =C5+0.5*C6 -> 14 | D10: =D5+0.5*D6 -> 5
A11: % de cumplimiento | B11: =IF(B9=0,0,B10/B9) -> 0.11111111 | C11: =IF(C9=0,0,C10/C9) -> 0.38888889 | D11: =IF(D9=0,0,D10/D9) -> 0.13888889
A13: Ranking | B13: =RANK(B10,$B$10:$D$10) -> 3 | C13: =RANK(C10,$B$10:$D$10) -> 1 | D13: =RANK(D10,$B$10:$D$10) -> 2
A15: Observaciones clave
A16: Dannemann | B16: Sin chárter válido: Andes opera solo desde EZE; AR y JetSMART chárter pendientes (pide prórroga). Catering opcional, alojamiento de tripulación no incluido explícitamente, staff 04 y 05/04 no cotizado, nominación incompatible con el pliego.
A17: Buzios Tour | B17: Mejor alcance: JetSMART A321 de 195 pax desde AEP cubre todo el grupo. Es "documento de trabajo": sin horarios, sin vuelos de staff, sin políticas ni contingencias. Opción AR (169 pax) no alcanza el mínimo de 170.
A18: InMotion | B18: Única con vuelos de staff concretos. Chárter JetSMART A321 desde AEP, pero ida 07:02 fuera de franja; horarios idénticos a vuelos regulares JetSMART (confirmar que sea aeronave exclusiva). No informa capacidad, inclusiones, soporte, dietas ni políticas.
A19: Todas | B19: Ninguna presenta la documentación de II.2.1.1 (antecedentes, equipo, clientes, estatuto, poderes, patrimonio) ni plan de contingencia, políticas de cancelación/penalidad, validez y referencias.
A20: Pliego | B20: II.1 menciona "Servicio de activación stand ExpoAgro 2027" y II.2.4 habla de construcción/stand: errores de copiado a aclarar a los oferentes.
A23: Tras aclaraciones (29/10/2026)
A24: Estado | B24: Dannemann | C24: Buzios Tour | D24: InMotion
A25: Cumple | B25: =COUNTIF('Tras aclaraciones'!F$5:F$40,$A25) -> 21 | C25: =COUNTIF('Tras aclaraciones'!I$5:I$40,$A25) -> 17 | D25: =COUNTIF('Tras aclaraciones'!L$5:L$40,$A25) -> 18
A26: Parcial | B26: =COUNTIF('Tras aclaraciones'!F$5:F$40,$A26) -> 9 | C26: =COUNTIF('Tras aclaraciones'!I$5:I$40,$A26) -> 16 | D26: =COUNTIF('Tras aclaraciones'!L$5:L$40,$A26) -> 11
A27: No cumple | B27: =COUNTIF('Tras aclaraciones'!F$5:F$40,$A27) -> 5 | C27: =COUNTIF('Tras aclaraciones'!I$5:I$40,$A27) -> 3 | D27: =COUNTIF('Tras aclaraciones'!L$5:L$40,$A27) -> 7
A28: No informa | B28: =COUNTIF('Tras aclaraciones'!F$5:F$40,$A28) -> 1 | C28: =COUNTIF('Tras aclaraciones'!I$5:I$40,$A28) -> 0 | D28: =COUNTIF('Tras aclaraciones'!L$5:L$40,$A28) -> 0
A29: Total requisitos | B29: =SUM(B25:B28) -> 36 | C29: =SUM(C25:C28) -> 36 | D29: =SUM(D25:D28) -> 36
A30: Puntaje (Cumple + ½ Parcial) | B30: =B25+0.5*B26 -> 25.5 | C30: =C25+0.5*C26 -> 25 | D30: =D25+0.5*D26 -> 23.5
A31: % de cumplimiento | B31: =IF(B29=0,0,B30/B29) -> 0.70833333 | C31: =IF(C29=0,0,C30/C29) -> 0.69444444 | D31: =IF(D29=0,0,D30/D29) -> 0.65277778
A32: Variación vs. inicial (p.p.) | B32: =B31-B11 -> 0.59722222 | C32: =C31-C11 -> 0.30555556 | D32: =D31-D11 -> 0.51388889
A33: Ranking | B33: =RANK(B30,$B$30:$D$30) -> 1 | C33: =RANK(C30,$B$30:$D$30) -> 2 | D33: =RANK(D30,$B$30:$D$30) -> 3
A35: Inconsistencias entre agencias | B35: Andes desde AEP: Buzios dice que es posible por USD 12.000 extra; Dannemann dice que opera solo desde EZE. JetSMART A321: Buzios informa 195 plazas, InMotion 200, Dannemann no tiene el modelo. Conviene validarlo directamente con las aerolíneas.
A36: Sin resolver en ninguna | B36: Documentación del punto II.2.1.1, habilitación ANAC adjunta y firma certificada por escribano. Para el staff, todas aclaran que la tarifa individual no se congela ni admite cambio de nombre: hay que nominar y emitir antes de las 2 semanas.

Sheet Tras aclaraciones
A1: Comparativo tras las aclaraciones (respuestas recibidas el 29/10/2026)
A2: Dannemann: evaluado sobre la opción Andes (la única con datos). Su nueva opción JetSMART tiene casi todo pendiente. Las columnas "Inicial" vienen de la hoja Comparativo.
A4: # | B4: Bloque | C4: Ref. pliego | D4: Requisito | E4: Dannemann – Inicial | F4: Dannemann – Actual | G4: Dannemann – Detalle | H4: Buzios – Inicial | I4: Buzios – Actual | J4: Buzios – Detalle | K4: InMotion – Inicial | L4: InMotion – Actual | M4: InMotion – Detalle
A5: 1 | B5: Aeronave y operación | C5: II.3 §1 / §3.1 | D5: Chárter desde/hacia Aeroparque (AEP) | E5: =Comparativo!E5 -> No cumple | F5: No cumple | G5: Andes sigue operando solo desde EZE (Buzios dice que puede salir de AEP; hay que verificarlo). Nueva opción JetSMART desde AEP, sin avión ni condiciones confirmadas. | H5: =Comparativo!G5 -> Parcial | I5: Cumple | J5: Andes puede salir de AEP con USD 12.000 extra. JetSMART y AR, desde AEP. | K5: =Comparativo!I5 -> Cumple | L5: Cumple | M5: JetSMART A321 desde AEP.
A6: 2 | B6: Aeronave y operación | C6: II.3 §1 | D6: Capacidad chárter ≥170 pax (ideal 195) | E6: =Comparativo!E6 -> Cumple | F6: Parcial | G6: Andes 183. JetSMART 195 pax en un solo vuelo, con avión pendiente de confirmar. | H6: =Comparativo!G6 -> Parcial | I6: Parcial | J6: AR sigue en 169 (pendiente). Andes 183. JetSMART 195. | K6: =Comparativo!I6 -> No informa | L6: Cumple | M6: A321 de 200 plazas: entran los 195.
A7: 3 | B7: Aeronave y operación | C7: II.3 §3.1 | D7: Tipo, modelo, línea aérea, capacidad y configuración de cabina | E7: =Comparativo!E7 -> Parcial | F7: Parcial | G7: Andes 737-800 NG, 183 plazas en clase única. JetSMART: modelo y configuración pendientes. | H7: =Comparativo!G7 -> Parcial | I7: Parcial | J7: JetSMART: 195 plazas en clase turista. Sin configuración para AR ni Andes. | K7: =Comparativo!I7 -> Parcial | L7: Parcial | M7: 200 plazas; no detalla configuración.
A8: 4 | B8: Aeronave y operación | C8: II.3 §2.1 | D8: Horarios dentro de la franja 12:00–18:00 (ida 06/04 y regreso 08/04) | E8: =Comparativo!E8 -> No informa | F8: Parcial | G8: Andes podría operar en la franja (aprobación en 48 h). JetSMART pendiente. Sin horarios concretos. | H8: =Comparativo!G8 -> No informa | I8: Cumple | J8: Ida 12:30–14:45 y regreso 14:30–16:40, sujetos a slots. | K8: =Comparativo!I8 -> Parcial | L8: Parcial | M8: Pedirán la franja de 12 a 18 h a JetSMART; sin horario concreto ni garantía.
A9: 5 | B9: Aeronave y operación | C9: II.3 §3.1 | D9: Operador habilitado por ANAC para vuelos no regulares (con habilitación) | E9: =Comparativo!E9 -> No informa | F9: Parcial | G9: Andes declara permisos incluidos; no adjunta habilitación. | H9: =Comparativo!G9 -> Parcial | I9: Parcial | J9: Son aerolíneas regulares; los permisos se tramitan al aceptar. No adjunta habilitación. | K9: =Comparativo!I9 -> No informa | L9: Parcial | M9: No la compartieron; aerolínea regular con la ruta habilitada.
A10: 6 | B10: Aeronave y operación | C10: II.3 §3.1 | D10: Ferry o permanencia de la aeronave en destino incluida | E10: =Comparativo!E10 -> Parcial | F10: Cumple | G10: Andes: avión y tripulación quedan en BRC, incluido. JetSMART pendiente. | H10: =Comparativo!G10 -> Cumple | I10: Cumple | J10: Incluido según la modalidad de cada alternativa. | K10: =Comparativo!I10 -> No informa | L10: Cumple | M10: El avión vuelve a BA o sigue en su red regular; incluido.
A11: 7 | B11: Aeronave y operación | C11: II.3 §3.1 | D11: Combustible y costos operativos incluidos | E11: =Comparativo!E11 -> No informa | F11: Cumple | G11: Andes: incluido. JetSMART: a cargo de la compañía. | H11: =Comparativo!G11 -> Parcial | I11: Cumple | J11: Precio cerrado: incluido. | K11: =Comparativo!I11 -> No informa | L11: Cumple | M11: Todo contemplado.
A12: 8 | B12: Aeronave y operación | C12: II.3 §3.1 | D12: Franquicia de equipaje (mano y despachado: piezas y peso) | E12: =Comparativo!E12 -> Parcial | F12: Cumple | G12: Andes: 5 kg a bordo + 15 kg en bodega (la franquicia más baja). JetSMART: 10 + 20 kg. | H12: =Comparativo!G12 -> No informa | I12: Cumple | J12: AR 8+20 kg · JetSMART 10+20 kg · Andes 8+20 kg. | K12: =Comparativo!I12 -> No informa | L12: Cumple | M12: Chárter 8+20 kg · Staff 8+15 kg.
A13: 9 | B13: Tripulación | C13: II.3 §3.2 | D13: Gastos de tripulación (honorarios, viáticos, alojamiento, traslados, comidas) incluidos | E13: =Comparativo!E13 -> No cumple | F13: Cumple | G13: Andes: alojamiento de la tripulación y traslados incluidos y gestionados por la agencia. JetSMART pendiente. | H13: =Comparativo!G13 -> Cumple | I13: Cumple | J13: Incluido. | K13: =Comparativo!I13 -> No informa | L13: Cumple | M13: Sin pernocte de tripulación; todo incluido.
A14: 10 | B14: Llave en mano | C14: II.3 §3.3 | D14: Permisos ANAC, tasas aeroportuarias, aterrizaje, estacionamiento, pernocte | E14: =Comparativo!E14 -> No informa | F14: Cumple | G14: Andes: incluido. JetSMART pendiente. | H14: =Comparativo!G14 -> Cumple | I14: Cumple | J14: Incluido. | K14: =Comparativo!I14 -> No informa | L14: Cumple | M14: Incluido.
A15: 11 | B15: Llave en mano | C15: II.3 §3.3 | D15: Handling, rampa, check-in y despacho (AA2000, Intercargo, PSA, EANA) | E15: =Comparativo!E15 -> No informa | F15: Cumple | G15: Andes: incluido. JetSMART pendiente. | H15: =Comparativo!G15 -> Parcial | I15: Cumple | J15: Incluido (AA2000, Intercargo, PSA, EANA). | K15: =Comparativo!I15 -> No informa | L15: Cumple | M15: Incluido.
A16: 12 | B16: Llave en mano | C16: II.3 §3.3 | D16: Seguros (aeronave, pasajeros, responsabilidad civil) | E16: =Comparativo!E16 -> No informa | F16: Cumple | G16: Andes: incluido. JetSMART pendiente. | H16: =Comparativo!G16 -> Parcial | I16: Cumple | J16: Incluido. | K16: =Comparativo!I16 -> No informa | L16: Cumple | M16: Incluido.
... A40: 36 | B40: Formalidades | C40: II.2.1 / II.5 | D40: PDF firmado, firma certificada y legalizada por escribano | E40: =Comparativo!E40 -> Parcial | F40: Parcial | G40: Carta firmada; sin certificación notarial. | H40: =Comparativo!G40 -> No cumple | I40: Parcial | J40: Firmada por el Presidente; sin certificación notarial. | K40: =Comparativo!I40 -> No cumple | L40: Parcial | M40: Firmada por la Jefa Comercial; sin certificación notarial.

Sheet Comparativo
A1: Vuelos Evento Bariloche 2027 – Comparativo técnico de propuestas vs. Pliego (Anexo 7, Parte II.3)
A2: Fuente: propuestas técnicas de Viajes Dannemann (23/10/2026), Buzios Tour (oct-2026) e InMotion. Estados: Cumple / Parcial / No cumple / No informa.
A4: # | B4: Bloque | C4: Ref. pliego | D4: Requisito | E4: Dannemann – Estado | F4: Dannemann – Detalle | G4: Buzios – Estado | H4: Buzios – Detalle | I4: InMotion – Estado | J4: InMotion – Detalle
A5: 1 | B5: Aeronave y operación | C5: II.3 §1 / §3.1 | D5: Chárter desde/hacia Aeroparque (AEP) | E5: No cumple | F5: Única opción chárter: Andes desde Ezeiza (no tiene amarre en AEP). Cotizaciones chárter de AR y JetSMART pendientes; pide prórroga. | G5: Parcial | H5: 3 alternativas: AR (AEP), Andes (EZE), JetSMART (AEP). Solo AR y JetSMART cumplen AEP. | I5: Cumple | J5: JetSMART A321, Aeroparque–Bariloche–Aeroparque.
A6: 2 | B6: Aeronave y operación | C6: II.3 §1 | D6: Capacidad chárter ≥170 pax (ideal 195) | E6: Cumple | F6: Andes B737-800 NG: 183 pax. | G6: Parcial | H6: AR 737-800: 169 pax (no llega a 170). Andes: 183. JetSMART A321: 195 (cumple total). | I6: No informa | J6: No informa la capacidad del A321 ni la configuración de cabina.
A7: 3 | B7: Aeronave y operación | C7: II.3 §3.1 | D7: Tipo, modelo, línea aérea, capacidad y configuración de cabina | E7: Parcial | F7: Indica aeronave, operador y capacidad; falta configuración de cabina. | G7: Parcial | H7: Indica aeronave, operador y capacidad por alternativa; falta configuración de cabina. | I7: Parcial | J7: Solo indica A321 y JetSMART.
A8: 4 | B8: Aeronave y operación | C8: II.3 §2.1 | D8: Horarios dentro de la franja 12:00–18:00 (ida 06/04 y regreso 08/04) | E8: No informa | F8: "Se confirmarán según disponibilidad de recursos". | G8: No informa | H8: No propone horarios del chárter. | I8: Parcial | J8: Ida 07:02–09:27 (fuera de franja). Regreso 17:40–19:47 (dentro de franja).
A9: 5 | B9: Aeronave y operación | C9: II.3 §3.1 | D9: Operador habilitado por ANAC para vuelos no regulares (con habilitación) | E9: No informa | F9: No adjunta habilitación ANAC de Andes. | G9: Parcial | H9: Declara "operador habilitado ANAC"; no adjunta habilitación. | I9: No informa | J9: No informa operador ni habilitación.
A10: 6 | B10: Aeronave y operación | C10: II.3 §3.1 | D10: Ferry o permanencia de la aeronave en destino incluida | E10: Parcial | F10: Indica que la aeronave permanece en Bariloche; no aclara si el costo está incluido. | G10: Cumple | H10: Declara ferry o estadía incluidos. | I10: No informa | J10: No lo menciona.
A11: 7 | B11: Aeronave y operación | C11: II.3 §3.1 | D11: Combustible y costos operativos incluidos | E11: No informa | F11: No lo declara. | G11: Parcial | H11: Declara gastos aeroportuarios de la aeronave incluidos; no menciona combustible explícitamente. | I11: No informa | J11: No lo menciona.
A12: 8 | B12: Aeronave y operación | C12: II.3 §3.1 | D12: Franquicia de equipaje (mano y despachado: piezas y peso) | E12: Parcial | F12: Solo indica "equipaje despachado" en vuelos regulares; sin piezas ni peso. Nada para el chárter. | G12: No informa | H12: No la informa. | I12: No informa | J12: No la informa.
A13: 9 | B13: Tripulación | C13: II.3 §3.2 | D13: Gastos de tripulación (honorarios, viáticos, alojamiento, traslados, comidas) incluidos | E13: No cumple | F13: Indica que la operación "requiere" 10 habitaciones single x 2 noches y traslados para la tripulación, sin aclarar que estén incluidos (riesgo de costo extra para VW). | G13: Cumple | H13: Declara tripulación, hotelería y traslados de tripulación incluidos. | I13: No informa | J13: No lo menciona.
A14: 10 | B14: Llave en mano | C14: II.3 §3.3 | D14: Permisos ANAC, tasas aeroportuarias, aterrizaje, estacionamiento, pernocte | E14: No informa | F14: No lo declara. | G14: Cumple | H14: Declara tasas e impuestos aeroportuarios incluidos. | I14: No informa | J14: No lo menciona.
A15: 11 | B15: Llave en mano | C15: II.3 §3.3 | D15: Handling, rampa, check-in y despacho (AA2000, Intercargo, PSA, EANA) | E15: No informa | F15: No lo declara. | G15: Parcial | H15: Declara gastos aeroportuarios incluidos, sin detalle. | I15: No informa | J15: No lo menciona.
A16: 12 | B16: Llave en mano | C16: II.3 §3.3 | D16: Seguros (aeronave, pasajeros, responsabilidad civil) | E16: No informa | F16: No lo declara. | G16: Parcial | H16: Declara seguros incluidos; no detalla coberturas. | I16: No informa | J16: No lo menciona.
... A40: 36 | B40: Formalidades | C40: II.2.1 / II.5 | D40: PDF firmado, firma certificada y legalizada por escribano | E40: Parcial | F40: Carta firmada por el Director General; sin certificación notarial visible. | G40: No cumple | H40: Presentación sin firma ("documento de trabajo"). | I40: No cumple | J40: Presentación sin firma.

Sheet Alternativas aéreas
A1: Alternativas de vuelo propuestas
A3: Agencia | B3: Tipo | C3: Aerolínea / operador | D3: Aeronave | E3: Capacidad (pax) | F3: Aeropuerto BA | G3: Tramo | H3: Fecha | I3: Horario | J3: Pax excedentes a vuelo regular | K3: Cumple AEP | L3: Cumple ≥170 pax | M3: Horario en franja 12–18
A4: Dannemann | B4: Chárter | C4: Andes Líneas Aéreas | D4: Boeing 737-800 NG | E4: 183 | F4: EZE | G4: Ida/Regreso | H4: 06/04 – 08/04 | I4: A confirmar | J4: 12 | K4: No | L4: Sí | M4: No informa
A5: Dannemann | B5: Chárter | C5: Aerolíneas Argentinas | D5: — | E5: No informa | F5: AEP | G5: — | H5: — | I5: Cotización pendiente | J5: No informa | K5: — | L5: — | M5: —
A6: Dannemann | B6: Chárter | C6: JetSMART | D6: — | E6: No informa | F6: AEP | G6: — | H6: — | I6: Cotización pendiente | J6: No informa | K6: — | L6: — | M6: —
A7: Dannemann | B7: Regular | C7: Aerolíneas Argentinas | D7: — | E7: No informa | F7: AEP | G7: Ida | H7: 06/04 | I7: 11:10 / 12:10 / 14:15 / 15:15 / 16:15 / 19:15 | J7: No informa | K7: Sí | L7: — | M7: —
A8: Dannemann | B8: Regular | C8: Aerolíneas Argentinas | D8: — | E8: No informa | F8: AEP | G8: Regreso | H8: 08/04 | I8: 09:25 / 11:25 / 14:25 / 15:25 / 17:30 / 20:30 | J8: No informa | K8: Sí | L8: — | M8: —
A9: Dannemann | B9: Regular | C9: JetSMART | D9: — | E9: No informa | F9: AEP | G9: Ida | H9: 06/04 | I9: 07:02 / 12:10 / 17:50 | J9: No informa | K9: Sí | L9: — | M9: —
A10: Dannemann | B10: Regular | C10: JetSMART | D10: — | E10: No informa | F10: AEP | G10: Regreso | H10: 08/04 | I10: 09:10 / 10:10 / 17:40 / 22:13 | J10: No informa | K10: Sí | L10: — | M10: —
A11: Buzios Tour | B11: Chárter | C11: Aerolíneas Argentinas | D11: Boeing 737-800 | E11: 169 | F11: AEP | G11: Ida/Regreso | H11: 06/04 – 08/04 | I11: No informa | J11: 26 | K11: Sí | L11: No | M11: No informa
A12: Buzios Tour | B12: Chárter | C12: Andes Líneas Aéreas | D12: Boeing 737-800 NG | E12: 183 | F12: EZE | G12: Ida/Regreso | H12: 06/04 – 08/04 | I12: No informa | J12: 12 | K12: No | L12: Sí | M12: No informa
A13: Buzios Tour | B13: Chárter | C13: JetSMART | D13: Airbus A321 | E13: 195 | F13: AEP | G13: Ida/Regreso | H13: 06/04 – 08/04 | I13: No informa | J13: 0 | K13: Sí | L13: Sí | M13: No informa
A14: InMotion | B14: Chárter | C14: JetSMART | D14: Airbus A321 | E14: No informa | F14: AEP | G14: Ida | H14: 06/04 | I14: 07:02 – 09:27 | J14: No informa | K14: Sí | L14: No informa | M14: No
A15: InMotion | B15: Chárter | C15: JetSMART | D15: Airbus A321 | E15: No informa | F15: AEP | G15: Regreso | H15: 08/04 | I15: 17:40 – 19:47 | J15: No informa | K15: Sí | L15: No informa | M15: Sí
A16: InMotion | B16: Staff A | C16: Aerolíneas Argentinas (AR1670 / AR1675) | D16: — | E16: 5 | F16: AEP | G16: Ida / Regreso | H16: 04/04 – 08/04 | I16: 09:20–11:45 / 15:25–17:30 | J16: No informa | K16: Sí | L16: n/a | M16: n/a
A17: InMotion | B17: Staff B | C17: Aerolíneas Argentinas (AR1672 / AR1675) | D17: — | E17: 5 | F17: AEP | G17: Ida / Regreso | H17: 05/04 – 08/04 | I17: 11:10–13:35 / 15:25–17:30 | J17: No informa | K17: Sí | L17: n/a | M17: n/a
